<metadata xml:lang="en"><Esri><CreaDate>20140130</CreaDate><CreaTime>12012700</CreaTime><ArcGISFormat>1.0</ArcGISFormat><ArcGISstyle>FGDC CSDGM Metadata</ArcGISstyle><SyncOnce>FALSE</SyncOnce><DataProperties><lineage><Process ToolSource="c:\program files (x86)\arcgis\desktop10.1\ArcToolbox\Toolboxes\Data Management Tools.tbx\Project" Date="20140130" Time="120127" Name="" export="">Project nsis D:\WMS\Maps\Data\NSIS_10km_WGS84.shp PROJCS['WGS_1984_Web_Mercator_Auxiliary_Sphere',GEOGCS['GCS_WGS_1984',DATUM['D_WGS_1984',SPHEROID['WGS_1984',6378137.0,298.257223563]],PRIMEM['Greenwich',0.0],UNIT['Degree',0.0174532925199433]],PROJECTION['Mercator_Auxiliary_Sphere'],PARAMETER['False_Easting',0.0],PARAMETER['False_Northing',0.0],PARAMETER['Central_Meridian',0.0],PARAMETER['Standard_Parallel_1',0.0],PARAMETER['Auxiliary_Sphere_Type',0.0],UNIT['Meter',1.0]] # PROJCS['OSGB 1936 / British National Grid',GEOGCS['OSGB 1936',DATUM['OSGB 1936',SPHEROID['Airy 1830',6377563.396,299.3249646]],PRIMEM['Greenwich',0.0],UNIT['degree',0.0174532925199433]],PROJECTION['Transverse_Mercator'],PARAMETER['false_easting',400000.0],PARAMETER['false_northing',-100000.0],PARAMETER['central_meridian',-2.0],PARAMETER['scale_factor',0.9996012717],PARAMETER['latitude_of_origin',49.0],UNIT['m',1.0]]</Process><Process ToolSource="c:\program files (x86)\arcgis\desktop10.1\ArcToolbox\Toolboxes\Data Management Tools.tbx\CalculateField" Date="20140205" Time="151953" Name="" export="">CalculateField NSIS_10km_WGS84 TempJoin "[msg] &amp; "_" &amp; [mssg]" VB #</Process></lineage><itemProps><itemName Sync="TRUE">NSIS_10km_WGS84</itemName><imsContentType Sync="TRUE" export="False">002</imsContentType><nativeExtBox><westBL Sync="TRUE">-837736.877862</westBL><eastBL Sync="TRUE">-100701.213418</eastBL><southBL Sync="TRUE">7307508.272270</southBL><northBL Sync="TRUE">8552872.077498</northBL><exTypeCode Sync="TRUE">1</exTypeCode></nativeExtBox><itemSize Sync="TRUE">0.083</itemSize><itemLocation><linkage Sync="TRUE">file://\\GORGONZOLA\D$\WMS\Maps\Data\NSIS_10km_WGS84.shp</linkage><protocol Sync="TRUE">Local Area Network</protocol></itemLocation></itemProps><coordRef><type Sync="TRUE">Projected</type><geogcsn Sync="TRUE">GCS_WGS_1984</geogcsn><csUnits Sync="TRUE">Linear Unit: Meter (1.000000)</csUnits><projcsn Sync="TRUE">WGS_1984_Web_Mercator_Auxiliary_Sphere</projcsn><peXml Sync="TRUE">&lt;ProjectedCoordinateSystem xsi:type='typens:ProjectedCoordinateSystem' xmlns:xsi='http://www.w3.org/2001/XMLSchema-instance' xmlns:xs='http://www.w3.org/2001/XMLSchema' xmlns:typens='http://www.esri.com/schemas/ArcGIS/10.1'&gt;&lt;WKT&gt;PROJCS[&amp;quot;WGS_1984_Web_Mercator_Auxiliary_Sphere&amp;quot;,GEOGCS[&amp;quot;GCS_WGS_1984&amp;quot;,DATUM[&amp;quot;D_WGS_1984&amp;quot;,SPHEROID[&amp;quot;WGS_1984&amp;quot;,6378137.0,298.257223563]],PRIMEM[&amp;quot;Greenwich&amp;quot;,0.0],UNIT[&amp;quot;Degree&amp;quot;,0.0174532925199433]],PROJECTION[&amp;quot;Mercator_Auxiliary_Sphere&amp;quot;],PARAMETER[&amp;quot;False_Easting&amp;quot;,0.0],PARAMETER[&amp;quot;False_Northing&amp;quot;,0.0],PARAMETER[&amp;quot;Central_Meridian&amp;quot;,0.0],PARAMETER[&amp;quot;Standard_Parallel_1&amp;quot;,0.0],PARAMETER[&amp;quot;Auxiliary_Sphere_Type&amp;quot;,0.0],UNIT[&amp;quot;Meter&amp;quot;,1.0],AUTHORITY[&amp;quot;EPSG&amp;quot;,3857]]&lt;/WKT&gt;&lt;XOrigin&gt;-20037700&lt;/XOrigin&gt;&lt;YOrigin&gt;-30241100&lt;/YOrigin&gt;&lt;XYScale&gt;148923141.92838538&lt;/XYScale&gt;&lt;ZOrigin&gt;-100000&lt;/ZOrigin&gt;&lt;ZScale&gt;10000&lt;/ZScale&gt;&lt;MOrigin&gt;-100000&lt;/MOrigin&gt;&lt;MScale&gt;10000&lt;/MScale&gt;&lt;XYTolerance&gt;0.001&lt;/XYTolerance&gt;&lt;ZTolerance&gt;0.001&lt;/ZTolerance&gt;&lt;MTolerance&gt;0.001&lt;/MTolerance&gt;&lt;HighPrecision&gt;true&lt;/HighPrecision&gt;&lt;WKID&gt;102100&lt;/WKID&gt;&lt;LatestWKID&gt;3857&lt;/LatestWKID&gt;&lt;/ProjectedCoordinateSystem&gt;</peXml></coordRef></DataProperties><ModDate>20140206</ModDate><ModTime>12471200</ModTime><ArcGISProfile>FGDC</ArcGISProfile><scaleRange><minScale>500000</minScale><maxScale>50000</maxScale></scaleRange><scaleRange><minScale>500000</minScale><maxScale>50000</maxScale></scaleRange><SyncDate>20140205</SyncDate><SyncTime>16012300</SyncTime></Esri><mdContact xmlns=""><rpIndName>David Donnelly</rpIndName><rpOrgName>The James Hutton Institute</rpOrgName><rpPosName>Research Scientist</rpPosName><rpCntInfo><cntAddress><delPoint>Craigiebuckler</delPoint><city>Aberdeen</city><postCode>AB15 8QH</postCode><eMailAdd>david.donnelly@hutton.ac.uk</eMailAdd><country>gb</country></cntAddress><cntPhone><voiceNum>01224 395265</voiceNum></cntPhone></rpCntInfo><role><RoleCd value="009"/></role></mdContact><distInfo><distributor><distorFormat><formatVer>9.3</formatVer></distorFormat><distorTran><onLineSrc><orFunct><OnFunctCd value="003"/></orFunct></onLineSrc><offLineMed><medName><MedNameCd value="001"/></medName></offLineMed></distorTran><distorCont><rpIndName>David Donnelly</rpIndName><rpOrgName>The James Hutton Institute</rpOrgName><rpPosName>Research Scientist</rpPosName><rpCntInfo><cntAddress><delPoint>Craigiebuckler</delPoint><city>Aberdeen</city><postCode>AB15 8QH</postCode><eMailAdd>david.donnelly@hutton.ac.uk</eMailAdd><country>gb</country></cntAddress><cntPhone><voiceNum>01224 395265</voiceNum></cntPhone></rpCntInfo><role><RoleCd value="005"/></role></distorCont><distorOrdPrc><ordInstr>Contact david.donnelly@hutton.ac.uk</ordInstr><resFees>Subject to area and attributes required. See http://www.macaulayscientific.com/gis2_dataset_1a.php</resFees><ordTurn>Two weeks for license processing</ordTurn></distorOrdPrc></distributor><distFormat><formatName Sync="TRUE">Shapefile</formatName></distFormat><distTranOps><transSize Sync="TRUE">0.083</transSize></distTranOps></distInfo><dataIdInfo><idCitation xmlns=""><resTitle Sync="FALSE">National Soils Inventory for Scotland (NSIS1)</resTitle><resEd>2012</resEd><resEdDate>20120925</resEdDate><resRefDate><refDate>19810101</refDate><refDateType><DateTypCd value="001"/></refDateType></resRefDate><citRespParty xmlns=""><rpIndName>Colin Campbell</rpIndName><rpOrgName>The James Hutton Institute</rpOrgName><rpPosName>Head of Soils</rpPosName><rpCntInfo><cntAddress><delPoint>Craigiebuckler</delPoint><city>Aberdeen</city><postCode>AB15 8QH</postCode><eMailAdd>colin.campbell@hutton.ac.uk</eMailAdd><country>gb</country></cntAddress></rpCntInfo><role><RoleCd value="002"/></role></citRespParty><citRespParty xmlns=""><rpIndName>David Donnelly</rpIndName><rpOrgName>The James Hutton Institute</rpOrgName><rpPosName>Research Scientist</rpPosName><role><RoleCd value="009"/></role><rpCntInfo><cntAddress><delPoint>Craigiebuckler</delPoint><city>Aberdeen</city><postCode>AB15 8QH</postCode><eMailAdd>david.donnelly@hutton.ac.uk</eMailAdd><country>gb</country></cntAddress><cntPhone><voiceNum>01224 395265</voiceNum></cntPhone></rpCntInfo></citRespParty><resAltTitle>qmsoils</resAltTitle><date><createDate>19810101</createDate></date><presForm xmlns=""><PresFormCd value="005" Sync="TRUE"/></presForm></idCitation><idAbs>&lt;DIV STYLE="text-align:Left;"&gt;&lt;DIV&gt;&lt;DIV&gt;&lt;P&gt;&lt;SPAN&gt;The National Soils Inventory for Scotland (NSIS1) dataset presented here has been collected using sampling points arranged as a 10 km grid. A wide range of attributes are described, measured and analysed for each site. These range from contextual information describing the surrounding landscape (such as slope and vegetation), down to detailed chemical analyses of each horizon within the soil profile. There are 721 sites in total where soil occurs; where there is no soil at a particular 10 km sampling point, this point has not been included.&lt;/SPAN&gt;&lt;/P&gt;&lt;/DIV&gt;&lt;/DIV&gt;&lt;/DIV&gt;</idAbs><resConst><LegConsts xmlns=""><accessConsts><RestrictCd value="001"/></accessConsts><accessConsts><RestrictCd value="006"/></accessConsts><useConsts><RestrictCd value="001"/></useConsts><useConsts><RestrictCd value="006"/></useConsts></LegConsts></resConst><dataScale xmlns=""><equScale><rfDenom>250000</rfDenom></equScale></dataScale><descKeys KeyTypCd="005"><keyTyp><KeyTypCd value="005"/></keyTyp><keyword>soil</keyword><keyword>land form</keyword><keyword>base material</keyword></descKeys><themeKeys xmlns=""><keyword>soil</keyword><keyword>land form</keyword><keyword>base material</keyword></themeKeys><themeKeys xmlns=""><keyword>soil</keyword><keyword>land form</keyword><keyword>base material</keyword></themeKeys><descKeys KeyTypCd="002"><keyTyp><KeyTypCd value="002"/></keyTyp><keyword>Scotland</keyword></descKeys><placeKeys xmlns=""><keyword>Scotland</keyword></placeKeys><placeKeys xmlns=""><keyword>Scotland</keyword></placeKeys><searchKeys><keyword>soil</keyword><keyword>land form</keyword><keyword>base material</keyword><keyword>Scotland</keyword></searchKeys><idPurp>An inventory of Scotland's soils at a 10 kilometre interval.</idPurp><idCredit>Soil Survey of Scotland Staff. (1981). The James Hutton Institute (2014).</idCredit><envirDesc Sync="TRUE">Microsoft Windows 7 Version 6.1 (Build 7601) Service Pack 1; Esri ArcGIS 10.1.1.3143</envirDesc><dataLang><languageCode value="eng" Sync="TRUE"/><countryCode value="GBR" Sync="TRUE"/></dataLang><spatRpType><SpatRepTypCd value="001" Sync="TRUE"/></spatRpType><dataExt xmlns=""><geoEle xmlns=""><GeoBndBox esriExtentType="search"><exTypeCode Sync="TRUE">1</exTypeCode><westBL Sync="TRUE">-7.525518</westBL><eastBL Sync="TRUE">-0.904614</eastBL><northBL Sync="TRUE">60.680696</northBL><southBL Sync="TRUE">54.718941</southBL></GeoBndBox></geoEle></dataExt><dataChar><CharSetCd value="004"/></dataChar><resConst><Consts><useLimit>&lt;DIV STYLE="text-align:Left;"&gt;&lt;DIV&gt;&lt;DIV&gt;&lt;P&gt;&lt;SPAN&gt;This data is point data, 1:250,000 polygon data for the whole of Scotland is also available. This data is available under licence from Scotland's Soils website and it is free of charge for non-commercial purposes. Data may not be redistributed or shared without an appropriate license. For commercial use of this data please contact the James Hutton Institute for licensing information. Publication without a publishing license is a breach of copyright.&lt;/SPAN&gt;&lt;/P&gt;&lt;/DIV&gt;&lt;/DIV&gt;&lt;/DIV&gt;</useLimit></Consts></resConst><tpCat><TopicCatCd value="001"/></tpCat><tpCat><TopicCatCd value="002"/></tpCat><tpCat><TopicCatCd value="007"/></tpCat></dataIdInfo><dqInfo xmlns=""><dataLineage><statement>None</statement></dataLineage><dqScope><scpLvl><ScopeCd value="005"/></scpLvl></dqScope></dqInfo><eainfo><detailed Name="NSIS_10km_WGS84" xmlns=""><enttyp><enttypl Sync="TRUE">NSIS_10km_WGS84</enttypl><enttypt Sync="TRUE">Feature Class</enttypt><enttypc Sync="TRUE">3091</enttypc></enttyp><attr><attrlabl Sync="TRUE">FID</attrlabl><attalias Sync="TRUE">FID</attalias><attrtype Sync="TRUE">OID</attrtype><attwidth Sync="TRUE">4</attwidth><atprecis Sync="TRUE">0</atprecis><attscale Sync="TRUE">0</attscale><attrdef Sync="TRUE">Internal feature number.</attrdef><attrdefs Sync="TRUE">ESRI</attrdefs><attrdomv><udom Sync="TRUE">Sequential unique whole numbers that are automatically generated.</udom></attrdomv></attr><attr><attrlabl Sync="TRUE">Shape</attrlabl><attalias Sync="TRUE">Shape</attalias><attrtype Sync="TRUE">Geometry</attrtype><attwidth Sync="TRUE">0</attwidth><atprecis Sync="TRUE">0</atprecis><attscale Sync="TRUE">0</attscale><attrdef Sync="TRUE">Feature geometry.</attrdef><attrdefs Sync="TRUE">ESRI</attrdefs><attrdomv><udom Sync="TRUE">Coordinates defining the features.</udom></attrdomv></attr><attr><attrlabl Sync="TRUE">__gid</attrlabl><attalias Sync="TRUE">__gid</attalias><attrtype Sync="TRUE">Double</attrtype><attwidth Sync="TRUE">19</attwidth><atprecis Sync="TRUE">18</atprecis><attscale Sync="TRUE">17</attscale></attr><attr><attrlabl Sync="TRUE">profile_id</attrlabl><attalias Sync="TRUE">profile_id</attalias><attrtype Sync="TRUE">Double</attrtype><attwidth Sync="TRUE">19</attwidth><atprecis Sync="TRUE">18</atprecis><attscale Sync="TRUE">17</attscale></attr><attr><attrlabl Sync="TRUE">profile_ng</attrlabl><attalias Sync="TRUE">profile_ng</attalias><attrtype Sync="TRUE">String</attrtype><attwidth Sync="TRUE">254</attwidth><atprecis Sync="TRUE">0</atprecis><attscale Sync="TRUE">0</attscale></attr><attr><attrlabl Sync="TRUE">easting</attrlabl><attalias Sync="TRUE">easting</attalias><attrtype Sync="TRUE">Double</attrtype><attwidth Sync="TRUE">19</attwidth><atprecis Sync="TRUE">18</atprecis><attscale Sync="TRUE">17</attscale></attr><attr><attrlabl Sync="TRUE">northing</attrlabl><attalias Sync="TRUE">northing</attalias><attrtype Sync="TRUE">Double</attrtype><attwidth Sync="TRUE">19</attwidth><atprecis Sync="TRUE">18</atprecis><attscale Sync="TRUE">17</attscale></attr><attr><attrlabl Sync="TRUE">pit_loc_ac</attrlabl><attalias Sync="TRUE">pit_loc_ac</attalias><attrtype Sync="TRUE">String</attrtype><attwidth Sync="TRUE">254</attwidth><atprecis Sync="TRUE">0</atprecis><attscale Sync="TRUE">0</attscale></attr><attr><attrlabl Sync="TRUE">profile_da</attrlabl><attalias Sync="TRUE">profile_da</attalias><attrtype Sync="TRUE">Double</attrtype><attwidth Sync="TRUE">19</attwidth><atprecis Sync="TRUE">18</atprecis><attscale Sync="TRUE">17</attscale></attr><attr><attrlabl Sync="TRUE">site_ngr</attrlabl><attalias Sync="TRUE">site_ngr</attalias><attrtype Sync="TRUE">String</attrtype><attwidth Sync="TRUE">254</attwidth><atprecis Sync="TRUE">0</atprecis><attscale Sync="TRUE">0</attscale></attr><attr><attrlabl Sync="TRUE">site_name</attrlabl><attalias Sync="TRUE">site_name</attalias><attrtype Sync="TRUE">String</attrtype><attwidth Sync="TRUE">254</attwidth><atprecis Sync="TRUE">0</atprecis><attscale Sync="TRUE">0</attscale></attr><attr><attrlabl Sync="TRUE">site_no</attrlabl><attalias Sync="TRUE">site_no</attalias><attrtype Sync="TRUE">Double</attrtype><attwidth Sync="TRUE">19</attwidth><atprecis Sync="TRUE">18</atprecis><attscale Sync="TRUE">17</attscale></attr><attr><attrlabl Sync="TRUE">surv_a</attrlabl><attalias Sync="TRUE">surv_a</attalias><attrtype Sync="TRUE">String</attrtype><attwidth Sync="TRUE">254</attwidth><atprecis Sync="TRUE">0</atprecis><attscale Sync="TRUE">0</attscale></attr><attr><attrlabl Sync="TRUE">altitude</attrlabl><attalias Sync="TRUE">altitude</attalias><attrtype Sync="TRUE">Double</attrtype><attwidth Sync="TRUE">19</attwidth><atprecis Sync="TRUE">18</atprecis><attscale Sync="TRUE">17</attscale></attr><attr><attrlabl Sync="TRUE">slope</attrlabl><attalias Sync="TRUE">slope</attalias><attrtype Sync="TRUE">Double</attrtype><attwidth Sync="TRUE">19</attwidth><atprecis Sync="TRUE">18</atprecis><attscale Sync="TRUE">17</attscale></attr><attr><attrlabl Sync="TRUE">slope_form</attrlabl><attalias Sync="TRUE">slope_form</attalias><attrtype Sync="TRUE">String</attrtype><attwidth Sync="TRUE">254</attwidth><atprecis Sync="TRUE">0</atprecis><attscale Sync="TRUE">0</attscale></attr><attr><attrlabl Sync="TRUE">slope_type</attrlabl><attalias Sync="TRUE">slope_type</attalias><attrtype Sync="TRUE">String</attrtype><attwidth Sync="TRUE">254</attwidth><atprecis Sync="TRUE">0</atprecis><attscale Sync="TRUE">0</attscale></attr><attr><attrlabl Sync="TRUE">bearing</attrlabl><attalias Sync="TRUE">bearing</attalias><attrtype Sync="TRUE">Double</attrtype><attwidth Sync="TRUE">19</attwidth><atprecis Sync="TRUE">18</atprecis><attscale Sync="TRUE">17</attscale></attr><attr><attrlabl Sync="TRUE">aspect</attrlabl><attalias Sync="TRUE">aspect</attalias><attrtype Sync="TRUE">String</attrtype><attwidth Sync="TRUE">254</attwidth><atprecis Sync="TRUE">0</atprecis><attscale Sync="TRUE">0</attscale></attr><attr><attrlabl Sync="TRUE">assoc_symb</attrlabl><attalias Sync="TRUE">assoc_symb</attalias><attrtype Sync="TRUE">String</attrtype><attwidth Sync="TRUE">254</attwidth><atprecis Sync="TRUE">0</atprecis><attscale Sync="TRUE">0</attscale></attr><attr><attrlabl Sync="TRUE">series_sym</attrlabl><attalias Sync="TRUE">series_sym</attalias><attrtype Sync="TRUE">String</attrtype><attwidth Sync="TRUE">254</attwidth><atprecis Sync="TRUE">0</atprecis><attscale Sync="TRUE">0</attscale></attr><attr><attrlabl Sync="TRUE">non_soil</attrlabl><attalias Sync="TRUE">non_soil</attalias><attrtype Sync="TRUE">String</attrtype><attwidth Sync="TRUE">254</attwidth><atprecis Sync="TRUE">0</atprecis><attscale Sync="TRUE">0</attscale></attr><attr><attrlabl Sync="TRUE">series_cod</attrlabl><attalias Sync="TRUE">series_cod</attalias><attrtype Sync="TRUE">Double</attrtype><attwidth Sync="TRUE">19</attwidth><atprecis Sync="TRUE">18</atprecis><attscale Sync="TRUE">17</attscale></attr><attr><attrlabl Sync="TRUE">MSG</attrlabl><attalias Sync="TRUE">msg</attalias><attrtype Sync="TRUE">String</attrtype><attwidth Sync="TRUE">254</attwidth><atprecis Sync="TRUE">0</atprecis><attscale Sync="TRUE">0</attscale></attr><attr><attrlabl Sync="TRUE">MSSG</attrlabl><attalias Sync="TRUE">mssg</attalias><attrtype Sync="TRUE">String</attrtype><attwidth Sync="TRUE">254</attwidth><atprecis Sync="TRUE">0</atprecis><attscale Sync="TRUE">0</attscale></attr><attr><attrlabl Sync="TRUE">gley_sg</attrlabl><attalias Sync="TRUE">gley_sg</attalias><attrtype Sync="TRUE">Double</attrtype><attwidth Sync="TRUE">19</attwidth><atprecis Sync="TRUE">18</atprecis><attscale Sync="TRUE">17</attscale></attr><attr><attrlabl Sync="TRUE">soil_phase</attrlabl><attalias Sync="TRUE">soil_phase</attalias><attrtype Sync="TRUE">Double</attrtype><attwidth Sync="TRUE">19</attwidth><atprecis Sync="TRUE">18</atprecis><attscale Sync="TRUE">17</attscale></attr><attr><attrlabl Sync="TRUE">soil_drain</attrlabl><attalias Sync="TRUE">soil_drain</attalias><attrtype Sync="TRUE">String</attrtype><attwidth Sync="TRUE">254</attwidth><atprecis Sync="TRUE">0</atprecis><attscale Sync="TRUE">0</attscale></attr><attr><attrlabl Sync="TRUE">parent_mat</attrlabl><attalias Sync="TRUE">parent_mat</attalias><attrtype Sync="TRUE">String</attrtype><attwidth Sync="TRUE">254</attwidth><atprecis Sync="TRUE">0</atprecis><attscale Sync="TRUE">0</attscale></attr><attr><attrlabl Sync="TRUE">rock_1_typ</attrlabl><attalias Sync="TRUE">rock_1_typ</attalias><attrtype Sync="TRUE">Double</attrtype><attwidth Sync="TRUE">19</attwidth><atprecis Sync="TRUE">18</atprecis><attscale Sync="TRUE">17</attscale></attr><attr><attrlabl Sync="TRUE">rock_2_typ</attrlabl><attalias Sync="TRUE">rock_2_typ</attalias><attrtype Sync="TRUE">Double</attrtype><attwidth Sync="TRUE">19</attwidth><atprecis Sync="TRUE">18</atprecis><attscale Sync="TRUE">17</attscale></attr><attr><attrlabl Sync="TRUE">pit_base</attrlabl><attalias Sync="TRUE">pit_base</attalias><attrtype Sync="TRUE">String</attrtype><attwidth Sync="TRUE">254</attwidth><atprecis Sync="TRUE">0</atprecis><attscale Sync="TRUE">0</attscale></attr><attr><attrlabl Sync="TRUE">vegetation</attrlabl><attalias Sync="TRUE">vegetation</attalias><attrtype Sync="TRUE">String</attrtype><attwidth Sync="TRUE">254</attwidth><atprecis Sync="TRUE">0</atprecis><attscale Sync="TRUE">0</attscale></attr><attr><attrlabl Sync="TRUE">flushing</attrlabl><attalias Sync="TRUE">flushing</attalias><attrtype Sync="TRUE">String</attrtype><attwidth Sync="TRUE">254</attwidth><atprecis Sync="TRUE">0</atprecis><attscale Sync="TRUE">0</attscale></attr><attr><attrlabl Sync="TRUE">site_drain</attrlabl><attalias Sync="TRUE">site_drain</attalias><attrtype Sync="TRUE">String</attrtype><attwidth Sync="TRUE">254</attwidth><atprecis Sync="TRUE">0</atprecis><attscale Sync="TRUE">0</attscale></attr><attr><attrlabl Sync="TRUE">rockiness</attrlabl><attalias Sync="TRUE">rockiness</attalias><attrtype Sync="TRUE">String</attrtype><attwidth Sync="TRUE">254</attwidth><atprecis Sync="TRUE">0</atprecis><attscale Sync="TRUE">0</attscale></attr><attr><attrlabl Sync="TRUE">boulderine</attrlabl><attalias Sync="TRUE">boulderine</attalias><attrtype Sync="TRUE">String</attrtype><attwidth Sync="TRUE">254</attwidth><atprecis Sync="TRUE">0</atprecis><attscale Sync="TRUE">0</attscale></attr><attr><attrlabl Sync="TRUE">erosion_ty</attrlabl><attalias Sync="TRUE">erosion_ty</attalias><attrtype Sync="TRUE">String</attrtype><attwidth Sync="TRUE">254</attwidth><atprecis Sync="TRUE">0</atprecis><attscale Sync="TRUE">0</attscale></attr><attr><attrlabl Sync="TRUE">climate</attrlabl><attalias Sync="TRUE">climate</attalias><attrtype Sync="TRUE">String</attrtype><attwidth Sync="TRUE">254</attwidth><atprecis Sync="TRUE">0</atprecis><attscale Sync="TRUE">0</attscale></attr><attr><attrlabl Sync="TRUE">lca</attrlabl><attalias Sync="TRUE">lca</attalias><attrtype Sync="TRUE">String</attrtype><attwidth Sync="TRUE">254</attwidth><atprecis Sync="TRUE">0</atprecis><attscale Sync="TRUE">0</attscale></attr><attr><attrlabl Sync="TRUE">sheet_thir</attrlabl><attalias Sync="TRUE">sheet_thir</attalias><attrtype Sync="TRUE">Double</attrtype><attwidth Sync="TRUE">19</attwidth><atprecis Sync="TRUE">18</atprecis><attscale Sync="TRUE">17</attscale></attr><attr><attrlabl Sync="TRUE">district</attrlabl><attalias Sync="TRUE">district</attalias><attrtype Sync="TRUE">String</attrtype><attwidth Sync="TRUE">254</attwidth><atprecis Sync="TRUE">0</atprecis><attscale Sync="TRUE">0</attscale></attr><attr><attrlabl Sync="TRUE">batchid</attrlabl><attalias Sync="TRUE">batchid</attalias><attrtype Sync="TRUE">Double</attrtype><attwidth Sync="TRUE">19</attwidth><atprecis Sync="TRUE">18</atprecis><attscale Sync="TRUE">17</attscale></attr><attr><attrlabl Sync="TRUE">horz_id</attrlabl><attalias Sync="TRUE">horz_id</attalias><attrtype Sync="TRUE">Double</attrtype><attwidth Sync="TRUE">19</attwidth><atprecis Sync="TRUE">18</atprecis><attscale Sync="TRUE">17</attscale></attr><attr><attrlabl Sync="TRUE">horz_posit</attrlabl><attalias Sync="TRUE">horz_posit</attalias><attrtype Sync="TRUE">Double</attrtype><attwidth Sync="TRUE">19</attwidth><atprecis Sync="TRUE">18</atprecis><attscale Sync="TRUE">17</attscale></attr><attr><attrlabl Sync="TRUE">horz_type</attrlabl><attalias Sync="TRUE">horz_type</attalias><attrtype Sync="TRUE">String</attrtype><attwidth Sync="TRUE">254</attwidth><atprecis Sync="TRUE">0</atprecis><attscale Sync="TRUE">0</attscale></attr><attr><attrlabl Sync="TRUE">horz_symb</attrlabl><attalias Sync="TRUE">horz_symb</attalias><attrtype Sync="TRUE">String</attrtype><attwidth Sync="TRUE">254</attwidth><atprecis Sync="TRUE">0</atprecis><attscale Sync="TRUE">0</attscale></attr><attr><attrlabl Sync="TRUE">horz_top</attrlabl><attalias Sync="TRUE">horz_top</attalias><attrtype Sync="TRUE">Double</attrtype><attwidth Sync="TRUE">19</attwidth><atprecis Sync="TRUE">18</atprecis><attscale Sync="TRUE">17</attscale></attr><attr><attrlabl Sync="TRUE">horz_botto</attrlabl><attalias Sync="TRUE">horz_botto</attalias><attrtype Sync="TRUE">Double</attrtype><attwidth Sync="TRUE">19</attwidth><atprecis Sync="TRUE">18</atprecis><attscale Sync="TRUE">17</attscale></attr><attr><attrlabl Sync="TRUE">horz_plus</attrlabl><attalias Sync="TRUE">horz_plus</attalias><attrtype Sync="TRUE">String</attrtype><attwidth Sync="TRUE">254</attwidth><atprecis Sync="TRUE">0</atprecis><attscale Sync="TRUE">0</attscale></attr><attr><attrlabl Sync="TRUE">col_mat</attrlabl><attalias Sync="TRUE">col_mat</attalias><attrtype Sync="TRUE">String</attrtype><attwidth Sync="TRUE">254</attwidth><atprecis Sync="TRUE">0</atprecis><attscale Sync="TRUE">0</attscale></attr><attr><attrlabl Sync="TRUE">col_ped</attrlabl><attalias Sync="TRUE">col_ped</attalias><attrtype Sync="TRUE">Double</attrtype><attwidth Sync="TRUE">19</attwidth><atprecis Sync="TRUE">18</atprecis><attscale Sync="TRUE">17</attscale></attr><attr><attrlabl Sync="TRUE">col_dry</attrlabl><attalias Sync="TRUE">col_dry</attalias><attrtype Sync="TRUE">Double</attrtype><attwidth Sync="TRUE">19</attwidth><atprecis Sync="TRUE">18</atprecis><attscale Sync="TRUE">17</attscale></attr><attr><attrlabl Sync="TRUE">col_mot1</attrlabl><attalias Sync="TRUE">col_mot1</attalias><attrtype Sync="TRUE">String</attrtype><attwidth Sync="TRUE">254</attwidth><atprecis Sync="TRUE">0</atprecis><attscale Sync="TRUE">0</attscale></attr><attr><attrlabl Sync="TRUE">mot1_freq</attrlabl><attalias Sync="TRUE">mot1_freq</attalias><attrtype Sync="TRUE">String</attrtype><attwidth Sync="TRUE">254</attwidth><atprecis Sync="TRUE">0</atprecis><attscale Sync="TRUE">0</attscale></attr><attr><attrlabl Sync="TRUE">mot1_size</attrlabl><attalias Sync="TRUE">mot1_size</attalias><attrtype Sync="TRUE">String</attrtype><attwidth Sync="TRUE">254</attwidth><atprecis Sync="TRUE">0</atprecis><attscale Sync="TRUE">0</attscale></attr><attr><attrlabl Sync="TRUE">mot1_con</attrlabl><attalias Sync="TRUE">mot1_con</attalias><attrtype Sync="TRUE">String</attrtype><attwidth Sync="TRUE">254</attwidth><atprecis Sync="TRUE">0</atprecis><attscale Sync="TRUE">0</attscale></attr><attr><attrlabl Sync="TRUE">mot1_shar</attrlabl><attalias Sync="TRUE">mot1_shar</attalias><attrtype Sync="TRUE">String</attrtype><attwidth Sync="TRUE">254</attwidth><atprecis Sync="TRUE">0</atprecis><attscale Sync="TRUE">0</attscale></attr><attr><attrlabl Sync="TRUE">om</attrlabl><attalias Sync="TRUE">om</attalias><attrtype Sync="TRUE">String</attrtype><attwidth Sync="TRUE">254</attwidth><atprecis Sync="TRUE">0</atprecis><attscale Sync="TRUE">0</attscale></attr><attr><attrlabl Sync="TRUE">om_min</attrlabl><attalias Sync="TRUE">om_min</attalias><attrtype Sync="TRUE">String</attrtype><attwidth Sync="TRUE">254</attwidth><atprecis Sync="TRUE">0</atprecis><attscale Sync="TRUE">0</attscale></attr><attr><attrlabl Sync="TRUE">humose</attrlabl><attalias Sync="TRUE">humose</attalias><attrtype Sync="TRUE">String</attrtype><attwidth Sync="TRUE">254</attwidth><atprecis Sync="TRUE">0</atprecis><attscale Sync="TRUE">0</attscale></attr><attr><attrlabl Sync="TRUE">hum_gr</attrlabl><attalias Sync="TRUE">hum_gr</attalias><attrtype Sync="TRUE">String</attrtype><attwidth Sync="TRUE">254</attwidth><atprecis Sync="TRUE">0</atprecis><attscale Sync="TRUE">0</attscale></attr><attr><attrlabl Sync="TRUE">sand_grain</attrlabl><attalias Sync="TRUE">sand_grain</attalias><attrtype Sync="TRUE">Double</attrtype><attwidth Sync="TRUE">19</attwidth><atprecis Sync="TRUE">18</atprecis><attscale Sync="TRUE">17</attscale></attr><attr><attrlabl Sync="TRUE">tex</attrlabl><attalias Sync="TRUE">tex</attalias><attrtype Sync="TRUE">String</attrtype><attwidth Sync="TRUE">254</attwidth><atprecis Sync="TRUE">0</atprecis><attscale Sync="TRUE">0</attscale></attr><attr><attrlabl Sync="TRUE">stru1_deg</attrlabl><attalias Sync="TRUE">stru1_deg</attalias><attrtype Sync="TRUE">String</attrtype><attwidth Sync="TRUE">254</attwidth><atprecis Sync="TRUE">0</atprecis><attscale Sync="TRUE">0</attscale></attr><attr><attrlabl Sync="TRUE">stru1_size</attrlabl><attalias Sync="TRUE">stru1_size</attalias><attrtype Sync="TRUE">String</attrtype><attwidth Sync="TRUE">254</attwidth><atprecis Sync="TRUE">0</atprecis><attscale Sync="TRUE">0</attscale></attr><attr><attrlabl Sync="TRUE">stru1_shap</attrlabl><attalias Sync="TRUE">stru1_shap</attalias><attrtype Sync="TRUE">String</attrtype><attwidth Sync="TRUE">254</attwidth><atprecis Sync="TRUE">0</atprecis><attscale Sync="TRUE">0</attscale></attr><attr><attrlabl Sync="TRUE">stru2_deg</attrlabl><attalias Sync="TRUE">stru2_deg</attalias><attrtype Sync="TRUE">Double</attrtype><attwidth Sync="TRUE">19</attwidth><atprecis Sync="TRUE">18</atprecis><attscale Sync="TRUE">17</attscale></attr><attr><attrlabl Sync="TRUE">stru2_size</attrlabl><attalias Sync="TRUE">stru2_size</attalias><attrtype Sync="TRUE">Double</attrtype><attwidth Sync="TRUE">19</attwidth><atprecis Sync="TRUE">18</atprecis><attscale Sync="TRUE">17</attscale></attr><attr><attrlabl Sync="TRUE">stru2_shap</attrlabl><attalias Sync="TRUE">stru2_shap</attalias><attrtype Sync="TRUE">Double</attrtype><attwidth Sync="TRUE">19</attwidth><atprecis Sync="TRUE">18</atprecis><attscale Sync="TRUE">17</attscale></attr><attr><attrlabl Sync="TRUE">moist</attrlabl><attalias Sync="TRUE">moist</attalias><attrtype Sync="TRUE">String</attrtype><attwidth Sync="TRUE">254</attwidth><atprecis Sync="TRUE">0</atprecis><attscale Sync="TRUE">0</attscale></attr><attr><attrlabl Sync="TRUE">con_wet</attrlabl><attalias Sync="TRUE">con_wet</attalias><attrtype Sync="TRUE">Double</attrtype><attwidth Sync="TRUE">19</attwidth><atprecis Sync="TRUE">18</atprecis><attscale Sync="TRUE">17</attscale></attr><attr><attrlabl Sync="TRUE">con_moist</attrlabl><attalias Sync="TRUE">con_moist</attalias><attrtype Sync="TRUE">String</attrtype><attwidth Sync="TRUE">254</attwidth><atprecis Sync="TRUE">0</atprecis><attscale Sync="TRUE">0</attscale></attr><attr><attrlabl Sync="TRUE">con_dry</attrlabl><attalias Sync="TRUE">con_dry</attalias><attrtype Sync="TRUE">Double</attrtype><attwidth Sync="TRUE">19</attwidth><atprecis Sync="TRUE">18</atprecis><attscale Sync="TRUE">17</attscale></attr><attr><attrlabl Sync="TRUE">ind</attrlabl><attalias Sync="TRUE">ind</attalias><attrtype Sync="TRUE">Double</attrtype><attwidth Sync="TRUE">19</attwidth><atprecis Sync="TRUE">18</atprecis><attscale Sync="TRUE">17</attscale></attr><attr><attrlabl Sync="TRUE">cem</attrlabl><attalias Sync="TRUE">cem</attalias><attrtype Sync="TRUE">Double</attrtype><attwidth Sync="TRUE">19</attwidth><atprecis Sync="TRUE">18</atprecis><attscale Sync="TRUE">17</attscale></attr><attr><attrlabl Sync="TRUE">rts1_freq</attrlabl><attalias Sync="TRUE">rts1_freq</attalias><attrtype Sync="TRUE">String</attrtype><attwidth Sync="TRUE">254</attwidth><atprecis Sync="TRUE">0</atprecis><attscale Sync="TRUE">0</attscale></attr><attr><attrlabl Sync="TRUE">rts1_size</attrlabl><attalias Sync="TRUE">rts1_size</attalias><attrtype Sync="TRUE">String</attrtype><attwidth Sync="TRUE">254</attwidth><atprecis Sync="TRUE">0</atprecis><attscale Sync="TRUE">0</attscale></attr><attr><attrlabl Sync="TRUE">rts1_kind</attrlabl><attalias Sync="TRUE">rts1_kind</attalias><attrtype Sync="TRUE">String</attrtype><attwidth Sync="TRUE">254</attwidth><atprecis Sync="TRUE">0</atprecis><attscale Sync="TRUE">0</attscale></attr><attr><attrlabl Sync="TRUE">rts2_freq</attrlabl><attalias Sync="TRUE">rts2_freq</attalias><attrtype Sync="TRUE">String</attrtype><attwidth Sync="TRUE">254</attwidth><atprecis Sync="TRUE">0</atprecis><attscale Sync="TRUE">0</attscale></attr><attr><attrlabl Sync="TRUE">rts2_size</attrlabl><attalias Sync="TRUE">rts2_size</attalias><attrtype Sync="TRUE">String</attrtype><attwidth Sync="TRUE">254</attwidth><atprecis Sync="TRUE">0</atprecis><attscale Sync="TRUE">0</attscale></attr><attr><attrlabl Sync="TRUE">rts2_kind</attrlabl><attalias Sync="TRUE">rts2_kind</attalias><attrtype Sync="TRUE">String</attrtype><attwidth Sync="TRUE">254</attwidth><atprecis Sync="TRUE">0</atprecis><attscale Sync="TRUE">0</attscale></attr><attr><attrlabl Sync="TRUE">sts1_freq</attrlabl><attalias Sync="TRUE">sts1_freq</attalias><attrtype Sync="TRUE">String</attrtype><attwidth Sync="TRUE">254</attwidth><atprecis Sync="TRUE">0</atprecis><attscale Sync="TRUE">0</attscale></attr><attr><attrlabl Sync="TRUE">sts1_size</attrlabl><attalias Sync="TRUE">sts1_size</attalias><attrtype Sync="TRUE">String</attrtype><attwidth Sync="TRUE">254</attwidth><atprecis Sync="TRUE">0</atprecis><attscale Sync="TRUE">0</attscale></attr><attr><attrlabl Sync="TRUE">sts1_shape</attrlabl><attalias Sync="TRUE">sts1_shape</attalias><attrtype Sync="TRUE">String</attrtype><attwidth Sync="TRUE">254</attwidth><atprecis Sync="TRUE">0</atprecis><attscale Sync="TRUE">0</attscale></attr><attr><attrlabl Sync="TRUE">sts1_lith</attrlabl><attalias Sync="TRUE">sts1_lith</attalias><attrtype Sync="TRUE">Double</attrtype><attwidth Sync="TRUE">19</attwidth><atprecis Sync="TRUE">18</atprecis><attscale Sync="TRUE">17</attscale></attr><attr><attrlabl Sync="TRUE">sts2_freq</attrlabl><attalias Sync="TRUE">sts2_freq</attalias><attrtype Sync="TRUE">String</attrtype><attwidth Sync="TRUE">254</attwidth><atprecis Sync="TRUE">0</atprecis><attscale Sync="TRUE">0</attscale></attr><attr><attrlabl Sync="TRUE">sts2_size</attrlabl><attalias Sync="TRUE">sts2_size</attalias><attrtype Sync="TRUE">String</attrtype><attwidth Sync="TRUE">254</attwidth><atprecis Sync="TRUE">0</atprecis><attscale Sync="TRUE">0</attscale></attr><attr><attrlabl Sync="TRUE">sts2_shape</attrlabl><attalias Sync="TRUE">sts2_shape</attalias><attrtype Sync="TRUE">String</attrtype><attwidth Sync="TRUE">254</attwidth><atprecis Sync="TRUE">0</atprecis><attscale Sync="TRUE">0</attscale></attr><attr><attrlabl Sync="TRUE">sts2_lith</attrlabl><attalias Sync="TRUE">sts2_lith</attalias><attrtype Sync="TRUE">Double</attrtype><attwidth Sync="TRUE">19</attwidth><atprecis Sync="TRUE">18</atprecis><attscale Sync="TRUE">17</attscale></attr><attr><attrlabl Sync="TRUE">bound_thic</attrlabl><attalias Sync="TRUE">bound_thic</attalias><attrtype Sync="TRUE">String</attrtype><attwidth Sync="TRUE">254</attwidth><atprecis Sync="TRUE">0</atprecis><attscale Sync="TRUE">0</attscale></attr><attr><attrlabl Sync="TRUE">bound_form</attrlabl><attalias Sync="TRUE">bound_form</attalias><attrtype Sync="TRUE">String</attrtype><attwidth Sync="TRUE">254</attwidth><atprecis Sync="TRUE">0</atprecis><attscale Sync="TRUE">0</attscale></attr><attr><attrlabl Sync="TRUE">sample_id</attrlabl><attalias Sync="TRUE">sample_id</attalias><attrtype Sync="TRUE">Double</attrtype><attwidth Sync="TRUE">19</attwidth><atprecis Sync="TRUE">18</atprecis><attscale Sync="TRUE">17</attscale></attr><attr><attrlabl Sync="TRUE">sample_pos</attrlabl><attalias Sync="TRUE">sample_pos</attalias><attrtype Sync="TRUE">Double</attrtype><attwidth Sync="TRUE">19</attwidth><atprecis Sync="TRUE">18</atprecis><attscale Sync="TRUE">17</attscale></attr><attr><attrlabl Sync="TRUE">sample_top</attrlabl><attalias Sync="TRUE">sample_top</attalias><attrtype Sync="TRUE">Double</attrtype><attwidth Sync="TRUE">19</attwidth><atprecis Sync="TRUE">18</atprecis><attscale Sync="TRUE">17</attscale></attr><attr><attrlabl Sync="TRUE">sample_bot</attrlabl><attalias Sync="TRUE">sample_bot</attalias><attrtype Sync="TRUE">Double</attrtype><attwidth Sync="TRUE">19</attwidth><atprecis Sync="TRUE">18</atprecis><attscale Sync="TRUE">17</attscale></attr><attr><attrlabl Sync="TRUE">loi</attrlabl><attalias Sync="TRUE">loi</attalias><attrtype Sync="TRUE">Double</attrtype><attwidth Sync="TRUE">19</attwidth><atprecis Sync="TRUE">18</atprecis><attscale Sync="TRUE">17</attscale></attr><attr><attrlabl Sync="TRUE">carbon</attrlabl><attalias Sync="TRUE">carbon</attalias><attrtype Sync="TRUE">Double</attrtype><attwidth Sync="TRUE">19</attwidth><atprecis Sync="TRUE">18</atprecis><attscale Sync="TRUE">17</attscale></attr><attr><attrlabl Sync="TRUE">nitrogen</attrlabl><attalias Sync="TRUE">nitrogen</attalias><attrtype Sync="TRUE">Double</attrtype><attwidth Sync="TRUE">19</attwidth><atprecis Sync="TRUE">18</atprecis><attscale Sync="TRUE">17</attscale></attr><attr><attrlabl Sync="TRUE">cn_ratio</attrlabl><attalias Sync="TRUE">cn_ratio</attalias><attrtype Sync="TRUE">Double</attrtype><attwidth Sync="TRUE">19</attwidth><atprecis Sync="TRUE">18</atprecis><attscale Sync="TRUE">17</attscale></attr><attr><attrlabl Sync="TRUE">organic_ma</attrlabl><attalias Sync="TRUE">organic_ma</attalias><attrtype Sync="TRUE">Double</attrtype><attwidth Sync="TRUE">19</attwidth><atprecis Sync="TRUE">18</atprecis><attscale Sync="TRUE">17</attscale></attr><attr><attrlabl Sync="TRUE">usbs_flag</attrlabl><attalias Sync="TRUE">usbs_flag</attalias><attrtype Sync="TRUE">String</attrtype><attwidth Sync="TRUE">254</attwidth><atprecis Sync="TRUE">0</atprecis><attscale Sync="TRUE">0</attscale></attr><attr><attrlabl Sync="TRUE">ubsand</attrlabl><attalias Sync="TRUE">ubsand</attalias><attrtype Sync="TRUE">Double</attrtype><attwidth Sync="TRUE">19</attwidth><atprecis Sync="TRUE">18</atprecis><attscale Sync="TRUE">17</attscale></attr><attr><attrlabl Sync="TRUE">ubsilt</attrlabl><attalias Sync="TRUE">ubsilt</attalias><attrtype Sync="TRUE">Double</attrtype><attwidth Sync="TRUE">19</attwidth><atprecis Sync="TRUE">18</atprecis><attscale Sync="TRUE">17</attscale></attr><attr><attrlabl Sync="TRUE">sand_int</attrlabl><attalias Sync="TRUE">sand_int</attalias><attrtype Sync="TRUE">Double</attrtype><attwidth Sync="TRUE">19</attwidth><atprecis Sync="TRUE">18</atprecis><attscale Sync="TRUE">17</attscale></attr><attr><attrlabl Sync="TRUE">silt_int</attrlabl><attalias Sync="TRUE">silt_int</attalias><attrtype Sync="TRUE">Double</attrtype><attwidth Sync="TRUE">19</attwidth><atprecis Sync="TRUE">18</atprecis><attscale Sync="TRUE">17</attscale></attr><attr><attrlabl Sync="TRUE">clay</attrlabl><attalias Sync="TRUE">clay</attalias><attrtype Sync="TRUE">Double</attrtype><attwidth Sync="TRUE">19</attwidth><atprecis Sync="TRUE">18</atprecis><attscale Sync="TRUE">17</attscale></attr><attr><attrlabl Sync="TRUE">texture_ps</attrlabl><attalias Sync="TRUE">texture_ps</attalias><attrtype Sync="TRUE">String</attrtype><attwidth Sync="TRUE">254</attwidth><atprecis Sync="TRUE">0</atprecis><attscale Sync="TRUE">0</attscale></attr><attr><attrlabl Sync="TRUE">ph_h2o</attrlabl><attalias Sync="TRUE">ph_h2o</attalias><attrtype Sync="TRUE">Double</attrtype><attwidth Sync="TRUE">19</attwidth><atprecis Sync="TRUE">18</atprecis><attscale Sync="TRUE">17</attscale></attr><attr><attrlabl Sync="TRUE">ph_cacl2</attrlabl><attalias Sync="TRUE">ph_cacl2</attalias><attrtype Sync="TRUE">Double</attrtype><attwidth Sync="TRUE">19</attwidth><atprecis Sync="TRUE">18</atprecis><attscale Sync="TRUE">17</attscale></attr><attr><attrlabl Sync="TRUE">exch_ca</attrlabl><attalias Sync="TRUE">exch_ca</attalias><attrtype Sync="TRUE">Double</attrtype><attwidth Sync="TRUE">19</attwidth><atprecis Sync="TRUE">18</atprecis><attscale Sync="TRUE">17</attscale></attr><attr><attrlabl Sync="TRUE">exch_mg</attrlabl><attalias Sync="TRUE">exch_mg</attalias><attrtype Sync="TRUE">Double</attrtype><attwidth Sync="TRUE">19</attwidth><atprecis Sync="TRUE">18</atprecis><attscale Sync="TRUE">17</attscale></attr><attr><attrlabl Sync="TRUE">exch_na</attrlabl><attalias Sync="TRUE">exch_na</attalias><attrtype Sync="TRUE">Double</attrtype><attwidth Sync="TRUE">19</attwidth><atprecis Sync="TRUE">18</atprecis><attscale Sync="TRUE">17</attscale></attr><attr><attrlabl Sync="TRUE">exch_k</attrlabl><attalias Sync="TRUE">exch_k</attalias><attrtype Sync="TRUE">Double</attrtype><attwidth Sync="TRUE">19</attwidth><atprecis Sync="TRUE">18</atprecis><attscale Sync="TRUE">17</attscale></attr><attr><attrlabl Sync="TRUE">exch_h</attrlabl><attalias Sync="TRUE">exch_h</attalias><attrtype Sync="TRUE">Double</attrtype><attwidth Sync="TRUE">19</attwidth><atprecis Sync="TRUE">18</atprecis><attscale Sync="TRUE">17</attscale></attr><attr><attrlabl Sync="TRUE">sum_cation</attrlabl><attalias Sync="TRUE">sum_cation</attalias><attrtype Sync="TRUE">Double</attrtype><attwidth Sync="TRUE">19</attwidth><atprecis Sync="TRUE">18</atprecis><attscale Sync="TRUE">17</attscale></attr><attr><attrlabl Sync="TRUE">base_sat</attrlabl><attalias Sync="TRUE">base_sat</attalias><attrtype Sync="TRUE">Double</attrtype><attwidth Sync="TRUE">19</attwidth><atprecis Sync="TRUE">18</atprecis><attscale Sync="TRUE">17</attscale></attr><attr><attrlabl Sync="TRUE">total_p2o5</attrlabl><attalias Sync="TRUE">total_p2o5</attalias><attrtype Sync="TRUE">Double</attrtype><attwidth Sync="TRUE">19</attwidth><atprecis Sync="TRUE">18</atprecis><attscale Sync="TRUE">17</attscale></attr><attr><attrlabl Sync="TRUE">nipaqua_ca</attrlabl><attalias Sync="TRUE">nipaqua_ca</attalias><attrtype Sync="TRUE">Double</attrtype><attwidth Sync="TRUE">19</attwidth><atprecis Sync="TRUE">18</atprecis><attscale Sync="TRUE">17</attscale></attr><attr><attrlabl Sync="TRUE">nipaqua_na</attrlabl><attalias Sync="TRUE">nipaqua_na</attalias><attrtype Sync="TRUE">Double</attrtype><attwidth Sync="TRUE">19</attwidth><atprecis Sync="TRUE">18</atprecis><attscale Sync="TRUE">17</attscale></attr><attr><attrlabl Sync="TRUE">nipaqua_k</attrlabl><attalias Sync="TRUE">nipaqua_k</attalias><attrtype Sync="TRUE">Double</attrtype><attwidth Sync="TRUE">19</attwidth><atprecis Sync="TRUE">18</atprecis><attscale Sync="TRUE">17</attscale></attr><attr><attrlabl Sync="TRUE">nipaqua_mg</attrlabl><attalias Sync="TRUE">nipaqua_mg</attalias><attrtype Sync="TRUE">Double</attrtype><attwidth Sync="TRUE">19</attwidth><atprecis Sync="TRUE">18</atprecis><attscale Sync="TRUE">17</attscale></attr><attr><attrlabl Sync="TRUE">nipaqua_cu</attrlabl><attalias Sync="TRUE">nipaqua_cu</attalias><attrtype Sync="TRUE">Double</attrtype><attwidth Sync="TRUE">19</attwidth><atprecis Sync="TRUE">18</atprecis><attscale Sync="TRUE">17</attscale></attr><attr><attrlabl Sync="TRUE">nipaqua_zn</attrlabl><attalias Sync="TRUE">nipaqua_zn</attalias><attrtype Sync="TRUE">Double</attrtype><attwidth Sync="TRUE">19</attwidth><atprecis Sync="TRUE">18</atprecis><attscale Sync="TRUE">17</attscale></attr><attr><attrlabl Sync="TRUE">nipaqua_fe</attrlabl><attalias Sync="TRUE">nipaqua_fe</attalias><attrtype Sync="TRUE">Double</attrtype><attwidth Sync="TRUE">19</attwidth><atprecis Sync="TRUE">18</atprecis><attscale Sync="TRUE">17</attscale></attr><attr><attrlabl Sync="TRUE">nipaqua_mn</attrlabl><attalias Sync="TRUE">nipaqua_mn</attalias><attrtype Sync="TRUE">Double</attrtype><attwidth Sync="TRUE">19</attwidth><atprecis Sync="TRUE">18</atprecis><attscale Sync="TRUE">17</attscale></attr><attr><attrlabl Sync="TRUE">nipaqua_al</attrlabl><attalias Sync="TRUE">nipaqua_al</attalias><attrtype Sync="TRUE">Double</attrtype><attwidth Sync="TRUE">19</attwidth><atprecis Sync="TRUE">18</atprecis><attscale Sync="TRUE">17</attscale></attr><attr><attrlabl Sync="TRUE">nipaqua_ph</attrlabl><attalias Sync="TRUE">nipaqua_ph</attalias><attrtype Sync="TRUE">Double</attrtype><attwidth Sync="TRUE">19</attwidth><atprecis Sync="TRUE">18</atprecis><attscale Sync="TRUE">17</attscale></attr><attr><attrlabl Sync="TRUE">nipaqua_ni</attrlabl><attalias Sync="TRUE">nipaqua_ni</attalias><attrtype Sync="TRUE">Double</attrtype><attwidth Sync="TRUE">19</attwidth><atprecis Sync="TRUE">18</atprecis><attscale Sync="TRUE">17</attscale></attr><attr><attrlabl Sync="TRUE">nipaqua_cd</attrlabl><attalias Sync="TRUE">nipaqua_cd</attalias><attrtype Sync="TRUE">Double</attrtype><attwidth Sync="TRUE">19</attwidth><atprecis Sync="TRUE">18</atprecis><attscale Sync="TRUE">17</attscale></attr><attr><attrlabl Sync="TRUE">nipaqua_cr</attrlabl><attalias Sync="TRUE">nipaqua_cr</attalias><attrtype Sync="TRUE">Double</attrtype><attwidth Sync="TRUE">19</attwidth><atprecis Sync="TRUE">18</atprecis><attscale Sync="TRUE">17</attscale></attr><attr><attrlabl Sync="TRUE">nipaqua_co</attrlabl><attalias Sync="TRUE">nipaqua_co</attalias><attrtype Sync="TRUE">Double</attrtype><attwidth Sync="TRUE">19</attwidth><atprecis Sync="TRUE">18</atprecis><attscale Sync="TRUE">17</attscale></attr><attr><attrlabl Sync="TRUE">nipaqua_pb</attrlabl><attalias Sync="TRUE">nipaqua_pb</attalias><attrtype Sync="TRUE">Double</attrtype><attwidth Sync="TRUE">19</attwidth><atprecis Sync="TRUE">18</atprecis><attscale Sync="TRUE">17</attscale></attr><attr><attrlabl Sync="TRUE">nipaqua_st</attrlabl><attalias Sync="TRUE">nipaqua_st</attalias><attrtype Sync="TRUE">Double</attrtype><attwidth Sync="TRUE">19</attwidth><atprecis Sync="TRUE">18</atprecis><attscale Sync="TRUE">17</attscale></attr><attr><attrlabl Sync="TRUE">nipaqua_mo</attrlabl><attalias Sync="TRUE">nipaqua_mo</attalias><attrtype Sync="TRUE">Double</attrtype><attwidth Sync="TRUE">19</attwidth><atprecis Sync="TRUE">18</atprecis><attscale Sync="TRUE">17</attscale></attr><attr><attrlabl Sync="TRUE">nipaqua_t</attrlabl><attalias Sync="TRUE">nipaqua_t</attalias><attrtype Sync="TRUE">Double</attrtype><attwidth Sync="TRUE">19</attwidth><atprecis Sync="TRUE">18</atprecis><attscale Sync="TRUE">17</attscale></attr><attr><attrlabl Sync="TRUE">nipaqua_ba</attrlabl><attalias Sync="TRUE">nipaqua_ba</attalias><attrtype Sync="TRUE">Double</attrtype><attwidth Sync="TRUE">19</attwidth><atprecis Sync="TRUE">18</atprecis><attscale Sync="TRUE">17</attscale></attr><attr><attrlabl Sync="TRUE">nipedta_cu</attrlabl><attalias Sync="TRUE">nipedta_cu</attalias><attrtype Sync="TRUE">Double</attrtype><attwidth Sync="TRUE">19</attwidth><atprecis Sync="TRUE">18</atprecis><attscale Sync="TRUE">17</attscale></attr><attr><attrlabl Sync="TRUE">nipedta_zn</attrlabl><attalias Sync="TRUE">nipedta_zn</attalias><attrtype Sync="TRUE">Double</attrtype><attwidth Sync="TRUE">19</attwidth><atprecis Sync="TRUE">18</atprecis><attscale Sync="TRUE">17</attscale></attr><attr><attrlabl Sync="TRUE">nipedta_mn</attrlabl><attalias Sync="TRUE">nipedta_mn</attalias><attrtype Sync="TRUE">Double</attrtype><attwidth Sync="TRUE">19</attwidth><atprecis Sync="TRUE">18</atprecis><attscale Sync="TRUE">17</attscale></attr><attr><attrlabl Sync="TRUE">nipedta_ni</attrlabl><attalias Sync="TRUE">nipedta_ni</attalias><attrtype Sync="TRUE">Double</attrtype><attwidth Sync="TRUE">19</attwidth><atprecis Sync="TRUE">18</atprecis><attscale Sync="TRUE">17</attscale></attr><attr><attrlabl Sync="TRUE">nipedta_cd</attrlabl><attalias Sync="TRUE">nipedta_cd</attalias><attrtype Sync="TRUE">Double</attrtype><attwidth Sync="TRUE">19</attwidth><atprecis Sync="TRUE">18</atprecis><attscale Sync="TRUE">17</attscale></attr><attr><attrlabl Sync="TRUE">nipedta_cr</attrlabl><attalias Sync="TRUE">nipedta_cr</attalias><attrtype Sync="TRUE">Double</attrtype><attwidth Sync="TRUE">19</attwidth><atprecis Sync="TRUE">18</atprecis><attscale Sync="TRUE">17</attscale></attr><attr><attrlabl Sync="TRUE">nipedta_pd</attrlabl><attalias Sync="TRUE">nipedta_pd</attalias><attrtype Sync="TRUE">Double</attrtype><attwidth Sync="TRUE">19</attwidth><atprecis Sync="TRUE">18</atprecis><attscale Sync="TRUE">17</attscale></attr><attr><attrlabl Sync="TRUE">par_mat_id</attrlabl><attalias Sync="TRUE">par_mat_id</attalias><attrtype Sync="TRUE">Double</attrtype><attwidth Sync="TRUE">19</attwidth><atprecis Sync="TRUE">18</atprecis><attscale Sync="TRUE">17</attscale></attr><attr><attrlabl Sync="TRUE">msg2013</attrlabl><attalias Sync="TRUE">msg2013</attalias><attrtype Sync="TRUE">String</attrtype><attwidth Sync="TRUE">254</attwidth><atprecis Sync="TRUE">0</atprecis><attscale Sync="TRUE">0</attscale></attr><attr><attrlabl Sync="TRUE">mssg2013</attrlabl><attalias Sync="TRUE">mssg2013</attalias><attrtype Sync="TRUE">String</attrtype><attwidth Sync="TRUE">254</attwidth><atprecis Sync="TRUE">0</atprecis><attscale Sync="TRUE">0</attscale></attr><attr><attrlabl Sync="TRUE">MAPSYMB</attrlabl><attalias Sync="TRUE">MAPSYMB</attalias><attrtype Sync="TRUE">String</attrtype><attwidth Sync="TRUE">18</attwidth><atprecis Sync="TRUE">0</atprecis><attscale Sync="TRUE">0</attscale></attr><attr><attrlabl Sync="TRUE">TempJoin</attrlabl><attalias Sync="TRUE">TempJoin</attalias><attrtype Sync="TRUE">String</attrtype><attwidth Sync="TRUE">50</attwidth><atprecis Sync="TRUE">0</atprecis><attscale Sync="TRUE">0</attscale></attr></detailed><overview xmlns=""><eaover>
Comma separated column descriptions:
COLUMN_NAME,NSIS_1 proforma_name,COMMENTS
MV_PROFILE_DATA_NSIS1_10KM_ID,,Unique identifier for row in MV_PROFILE_DATA_NSIS1_10KM. Use this field as a unique identifier for links to MS Access or if setting up an external database.
PROFILE_NGR,,Profile pit location by GPS Ordnance Survey National Grid Reference (NGR)
EASTING,,Easting in metres from the false origin of the Ordnance Survey National Grid. Derived from OSGB NGR
NORTHING,,Northing in metres from the false origin of the Ordnance Survey National Grid. Derived from OSGB NGR
PIT_LOC_ACC,Location of pit,Estimate of proximity to mark on air photograph. Only applies where sites were located using aerial photo.
PROFILE_DATE,Date,Date the profile was described and sampled. Currently recorded as VARCHAR(2) datatype.
SITE_NGR,Nat Grid,National Grid Reference of first visit to pristine soil profile. Subsequent visits to resample will have the same site_ngr.
SITE_NAME,Title,Name of locality where the profile was collected. The extent of locality ranges from small (e.g. experimental plot) to large (e.g. an island such as Lewis)
SITE_NO,Title No.,Used for multiple profiles having the same site_name. Not used for re-sampling of a particular individual profile which is given the same site_name and site_no
SURV_A,Surv,Lead author (soil surveyor) of profile description.
ALTITUDE,Alt,Profile elevation (height)
SLOPE,Slope in degrees,Slope at profile pit measured by abney level or clinometer
SLOPE_FORM,,Shape of land surface crossing profile pit assessed in upslope to downslope direction.
SLOPE_TYPE,,Slopes classed into two simple types (simple and complex) based on complexity of slopes around site.
BEARING,Aspect - bearing,Compass measurement in degrees along the line of maximum slope passing through the profile pit. Measured down the slope.
ASPECT,Aspect - degrees,Compass bearing translated to one of the 16 principal compass points
ASSOC_SYMB,Assoc,Association symbol comprising two letters. The symbol was generated for the legends on paper maps when the requirement was for each map to have a unique symbol-set. Resulting from this pre-database code allocation there are a small number of repeats in the codes where different associations have the same symbol. For a unique association identifier the first 3 characters of the field SERIES_CODE should be used.
SERIES_SYMB,Series,Series symbol comprising two letters. The symbol was generated for the legends on paper maps when the requirement was for each map to have a unique symbol-set. Resulting from this pre-database code allocation there are a small number of repeats where different series have the same symbol. For a unique series identifier the complete content of the field SERIES_CODE should be used.
NON_SOIL,Misc map units,Grid survey sites which were not soil profiles are recorded here. Version 1 field name was MMU
SERIES_CODE,,Unique numeric code for soil series.
MSG,,Major soil group based on Scottish Soil Classification (1984)
MSSG,,Major soil sub-group based on Scottish Soil Classification (1984)
GLEY_SG,,Gleying type based on Scottish Soil Classification (1984)
SOIL_PHASE,Phase,Soil phase was developed for mapping and has not been systematically applied throughout the soil profile database. The way we categorise phases of series and map units needs systemising. This will be tackled in Version 3 of the soil database.
SOIL_DRAINAGE,,Natural drainage of soil profile assessed from profile morphology alone.
PARENT_MATERIAL,Type of PM,Type of parent material
ROCK_1_TYPE,,Primary rock type in parent material
ROCK_2_TYPE,,Secondary rock type in parent material
PIT_BASE,Base of pit,Reason for stopping the profile pit excavation or states whether the soil profile continues beyond the profile pit base.
VEGETATION,,Vegetation according to A Key to the Common Plant Communities of Scotland J.S. Robertson (1984).
FLUSHING,,Evidence of flushing [Yes or No]. Based on the plant species at the site.
SITE_DRAINAGE,,Observed site hydrology in 3 classes [shedding; normal; receiving].
ROCKINESS,Rock outcrop,Rock outcrop class on land surface around profile pit. Proportion and spacing are both used.
BOULDERINESS,Boulders,Surface boulder class around profile pit. Number and spacing are both taken into account.
EROSION_TYPE,Erosion,Type of erosion.
CLIMATE,,Climate classification according to Birse (1971). In upland areas this was often done by field modification of map classes using vegetation growth and form.
LCA,,Field assessment of LCA class.
SHEET_THIRD,Sheet No.,Unique number identifier for Ordnance Survey third edition map sheet that profile occurs on.
DISTRICT,,Local authority district from a specific date (which was ????)
BATCHID,,Analytical batch identifier for pre-NSIS_2 profiles.
HORZ_ID,,Unique identifier for a horizon. Foreign key to several other tables.
HORZ_POSITION,,Horizons numbered in sequence from the surface horizon down
HORZ_TYPE,Profile scope,Indicates whether horizon was recorded in the field as organic or mineral. These two types have different data recorded.
HORZ_SYMB_FIELD,Horizon symbol,Horizon symbol allocated in the field
HORZ_TOP,,Measurement to the top of the horizon from the soil surface
HORZ_BOTTOM,Depth,Measurement to the bottom of the horizon from the soil surface
HORZ_PLUS,,A + sign is inserted here when the base of the horizon continued below the pit base
COL_MAT,Colour,Soil matrix Munsell colour
COL_PED,Colour,Soil ped Munsell colour
COL_DRY,Colour,Air-dry soil Munsell colour measured in field
COL_MOT1,Colour,Primary soil mottle Munsell colour
MOT1_FREQ,,Frequency class of primary mottles
MOT1_SIZE,,Size class of primary mottles
MOT1_CON,,Contrast between colour of primary mottles and colour of soil matrix
MOT1_SHAR,,Sharpness of the boundary between the primary mottles and the soil matrix judged by colour.
OM,Nature of OM,Nature of organic matter - 3 classes: amorphous; semi-fibrous; fibrous.
OM_MIN,,Mineral material in organic horizons
HUMOSE,,Field texture humose is recorded as H. Duplicates the data in HUM_GR which was carried over from the original data tables.
HUM_GR,,Superseded by humose and sand_grain fields. Will be dropped in Version 3.
SAND_GRAIN,,Field assessment of sand grains size in 3 classes. Null might be interpreted as medium. Duplicates the data in HUM_GR which was carried over from the original data tables.
TEX,Texture,Field texture class
STRU1_DEG,,The degree of ped development of the primary ped type
STRU1_SIZE,,Size class of the primary ped type
STRU1_SHAPE,,Shape class of the primary ped type
STRU2_DEG,,The degree of ped development of the secondary ped type
STRU2_SIZE,,Size class of the secondary ped type
STRU2_SHAPE,,Shape class of the secondary ped type
MOIST,,Field moisture state
CON_WET,,Consistence type when the field moisture state is wet
CON_MOIST,,Consistence type when the field moisture state is moist
CON_DRY,,Consistence type when the field moisture state is dry
IND,,Strength class of induration
CEM,,Strength class of cementation
RTS1_FREQ,,Frequency class of the primary roots
RTS1_SIZE,,Size class of the primary roots
RTS1_KIND,,Type of the primary roots
RTS2_FREQ,,Frequency class of the secondary roots
RTS2_SIZE,,Size class of the secondary roots
RTS2_KIND,,Type of the secondary roots
STS1_FREQ,,Primary stones frequency class
STS1_SIZE,,Primary stones size class
STS1_SHAPE,,Primary stones shape class
STS1_LITH,,Primary stones lithology code
STS2_FREQ,,Secondary stones frequency class
STS2_SIZE,,Secondary stones size class
STS2_SHAPE,,Secondary stones shape class
STS2_LITH,,Secondary stones lithology code
BOUND_THICK,Boundary thickness,Thickness of the horizon boundary with the underlying horizon.
BOUND_FORM,Boundary form,Irregularity of the horizon boundary with the underlying horizon.
SAMPLE_ID,Lab Nos.,Sample identifier formerly known as LABNO
SAMPLE_POSITION,,Sample position numbered from top down. Began recording this in NSIS_2 - should be complete for NSIS_1 profiles.
SAMPLE_TOP,Bulk samples and Extra bulk samples,Measurement to the top of the sample from the soil surface
SAMPLE_BOTTOM,Bulk samples and Extra bulk samples,Measurement to the bottom of the sample from the soil surface
LOI,,Loss on ignition according to method code DP1971
CARBON,,Total carbon percentage by wet combustion or CHN analyser
NITROGEN,,Total nitrogen percentage by CHN analyser
CN_RATIO,,Ratio of carbon to nitrogen
ORGANIC_MATTER,,Percentage organic matter content. Calculated by ROUND(C*1.721) adjusted to 100 in 5 samples where calculated value exceeds 100
USBS_FLAG,,Flag to indicate whether silt and sand boundary is USDA or BSTC i.e. 50 or 63 microns. This code is not consistently applied within the data base although the change was implemented in January 1986.
UBSAND,,Sand percentage either USDA or BSTC
UBSILT,,Silt percentage either USDA or BSTC
SAND_INT,,Sand percentage according to the International particle size classification which has sand as 20 to 2000 microns
SILT_INT,,Silt percentage according to the International particle size classification which has silt as 2 to 20 microns
CLAY,,Clay percentage. Clay particles are less than 2 microns.
TEXTURE_FROM_PSC,,Mineral texture class decoded from the measured particle size data. Organic content was not included and may differ from field texture assessment.
PH_H2O,,pH in water
PH_CACL2,,pH in 0.01M calcium chloride
EXCH_CALCIUM,,Exchangeable calcium (meq per 100g air-dried soil) according to method code DP1971
EXCH_MAGNESIUM,,Exchangeable magnesium (meq per 100g air-dried soil) according to method code DP1971
EXCH_SODIUM,,Exchangeable sodium (meq per 100g air-dried soil) according to method code DP1971
EXCH_POTASSIUM,,Exchangeable potassium (meq per 100g air-dried soil) according to method code DP1971
EXCH_HYDROGEN,,Exchangeable hydrogen (meq per 100g air-dried soil) according to method code DP1971
SUM_CATIONS,,Sum of cations calculated by ROUND((ca+mg+na+k+h)1)
BASE_SATURATION,,Base saturation. Appears to be calculated from ROUND((100*(ca+mg+na+k)/(ca+mg+na+k+h))1) WHERE h&lt;&gt;0 with 16 exceptions
TOTAL_P2O5,,Total P2O5 [mg per 100g air-dry soil]. Requires a conversion to total P
NIPAQUA_CALCIUM,,Calcium extracted by aqua-regia digestion [ppm in air-dried soil]
NIPAQUA_SODIUM,,Sodium extracted by aqua-regia digestion [ppm in air-dried soil]
NIPAQUA_POTASSIUM,,Potassium extracted by aqua-regia digestion [ppm in air-dried soil]
NIPAQUA_MAGNESIUM,,Magnesium extracted by aqua-regia digestion [ppm in air-dried soil]
NIPAQUA_COPPER,,Copper extracted by aqua-regia digestion [ppm in air-dried soil]
NIPAQUA_ZINC,,Zinc extracted by aqua-regia digestion [ppm in air-dried soil]
NIPAQUA_IRON,,Iron extracted by aqua-regia digestion [ppm in air-dried soil]
NIPAQUA_MANGANESE,,Manganese extracted by aqua-regia digestion [ppm in air-dried soil]
NIPAQUA_ALUMINIUM,,Aluminium extracted by aqua-regia digestion [ppm in air-dried soil]
NIPAQUA_PHOSPHORUS,,Phosphorus extracted by aqua-regia digestion [ppm in air-dried soil]
NIPAQUA_NICKEL,,Nickel extracted by aqua-regia digestion [ppm in air-dried soil]
NIPAQUA_CADMIUM,,Cadmium extracted by aqua-regia digestion [ppm in air-dried soil]
NIPAQUA_CHROMIUM,,Chromium extracted by aqua-regia digestion [ppm in air-dried soil]
NIPAQUA_COBALT,,Cobalt extracted by aqua-regia digestion [ppm in air-dried soil]
NIPAQUA_LEAD,,Lead extracted by aqua-regia digestion [ppm in air-dried soil]
NIPAQUA_STRONTIUM,,Strontium extracted by aqua-regia digestion [ppm in air-dried soil]
NIPAQUA_MOLYBDENUM,,Molybdenum extracted by aqua-regia digestion [ppm in air-dried soil]
NIPAQUA_TITANIUM,,Titanium extracted by aqua-regia digestion [ppm in air-dried soil]
NIPAQUA_BARIUM,,Barium extracted by aqua-regia digestion [ppm in air-dried soil]
NIPEDTA_COPPER,,Copper extracted by EDTA
NIPEDTA_ZINC,,Zinc extracted by EDTA
NIPEDTA_MANGANESE,,Manganese extracted by EDTA
NIPEDTA_NICKEL,,Nickel extracted by EDTA
NIPEDTA_CADMIUM,,Cadmium extracted by EDTA
NIPEDTA_CHROMIUM,,Chromium extracted by EDTA
NIPEDTA_LEAD,,Lead extracted by EDTA</eaover></overview></eainfo><mdLang><languageCode value="eng" Sync="TRUE"/><countryCode value="GBR" Sync="TRUE"/></mdLang><GEMINI_Metadata><IdentificationInfo><spatialRepresentationType codeList="001"/><extent><geographicElement><westBoundLongitude>-7.525518</westBoundLongitude><eastBoundLongitude>-0.904614</eastBoundLongitude><northBoundLatitude>60.680696</northBoundLatitude><southBoundLatitude>54.718941</southBoundLatitude></geographicElement></extent></IdentificationInfo><dateStamp>20140205</dateStamp><metadataStandardName>UK GEMINI Standard</metadataStandardName><metadataStandardVersion>1.0</metadataStandardVersion></GEMINI_Metadata><mdHrLv><ScopeCd value="005" Sync="TRUE"/></mdHrLv><mdHrLvName Sync="TRUE">dataset</mdHrLvName><refSysInfo><RefSystem><refSysID><identCode code="3857" Sync="TRUE"/><idCodeSpace Sync="TRUE">EPSG</idCodeSpace><idVersion Sync="TRUE">7.11.2</idVersion></refSysID></RefSystem></refSysInfo><spatRepInfo><VectSpatRep><geometObjs Name="NSIS_10km_WGS84"><geoObjTyp><GeoObjTypCd value="004" Sync="TRUE"/></geoObjTyp><geoObjCnt Sync="TRUE">3091</geoObjCnt></geometObjs><topLvl><TopoLevCd value="001" Sync="TRUE"/></topLvl></VectSpatRep></spatRepInfo><spdoinfo><ptvctinf><esriterm Name="NSIS_10km_WGS84"><efeatyp Sync="TRUE">Simple</efeatyp><efeageom code="1" Sync="TRUE"/><esritopo Sync="TRUE">FALSE</esritopo><efeacnt Sync="TRUE">3091</efeacnt><spindex Sync="TRUE">FALSE</spindex><linrefer Sync="TRUE">FALSE</linrefer></esriterm></ptvctinf></spdoinfo><mdDateSt Sync="TRUE">20140206</mdDateSt><gmd:GEMINI_Metadata xmlns:gmd="http://www.isotc211.org/2005/gmd" xmlns:xsi="http://www.w3.org/2001/XMLSchema-instance" xmlns:gco="http://www.isotc211.org/2005/gco" xmlns:srv="http://www.isotc211.org/2005/srv" xmlns:gts="http://www.isotc211.org/2005/gts" xmlns:gml="http://www.opengis.net/gml" xmlns:xlink="http://www.w3.org/1999/xlink" xmlns:msxsl="urn:schemas-microsoft-com:xslt"><gmd:hierarchyLevel><gmd:MD_ScopeCode codeList="http://standards.iso.org/ittf/PubliclyAvailableStandards/ISO_19139_Schemas/resources/Codelist/gmxCodelists.xml#MD_ScopeCode" codeListValue="dataset">Dataset</gmd:MD_ScopeCode></gmd:hierarchyLevel><gmd:dateStamp><gco:Date>2014-02-05</gco:Date></gmd:dateStamp><gmd:language><gmd:LanguageCode codeList="http://www.loc.gov/standards/iso639-2/php/code_list.php" codeListValue="eng">English</gmd:LanguageCode></gmd:language><gmd:identificationInfo><gmd:MD_DataIdentification><gmd:spatialResolution><gmd:MD_Resolution><gmd:distance><gco:Distance uom="Meters">6.71487310199837E-09</gco:Distance></gmd:distance></gmd:MD_Resolution></gmd:spatialResolution><gmd:citation><gmd:CI_Citation><gmd:title><gco:CharacterString>NSIS_10km_WGS84</gco:CharacterString></gmd:title></gmd:CI_Citation></gmd:citation><gmd:extent><gmd:EX_Extent><gmd:verticalElement><gmd:EX_VerticalExtent><gmd:minimumValue><gco:Real>-100000.00</gco:Real></gmd:minimumValue><gmd:maximumValue><gco:Real>900719825474.10</gco:Real></gmd:maximumValue></gmd:EX_VerticalExtent></gmd:verticalElement></gmd:EX_Extent></gmd:extent></gmd:MD_DataIdentification></gmd:identificationInfo><gmd:distributionInfo><gmd:MD_Distribution><gmd:transferOptions><gmd:MD_DigitalTransferOptions><gmd:onLine><gmd:CI_OnlineResource><gmd:linkage><gmd:URL>\\GORGONZOLA\D$\WMS\Maps\Data\NSIS_10km_WGS84.shp</gmd:URL></gmd:linkage></gmd:CI_OnlineResource></gmd:onLine></gmd:MD_DigitalTransferOptions></gmd:transferOptions></gmd:MD_Distribution></gmd:distributionInfo><gmd:referenceSystemInfo><gmd:MD_ReferenceSystem><gmd:referenceSystemIdentifier><gmd:RS_Identifier><gmd:code><gco:CharacterString>WGS_1984_Web_Mercator_Auxiliary_Sphere</gco:CharacterString></gmd:code></gmd:RS_Identifier></gmd:referenceSystemIdentifier></gmd:MD_ReferenceSystem></gmd:referenceSystemInfo></gmd:GEMINI_Metadata><mdChar><CharSetCd value="004"/></mdChar></metadata>
